{
    "jobs" :[
        {
            "id" :1,
            "title" : "Str. Developer" ,
            "salary" :5000,
            "location" :"Uzbekistan"
        },
        {
            "id" :2,
            "title" : "Frontend Developer" ,
            "salary" :3000,
            "location" :"Tashkent"
        },
        {
            "id" :3,
            "title" : "FullStack Developer" ,
            "salary" :6000,
            "location" :"London"
        },
        {
            "id" :4,
            "title" : "Backend Developer" ,
            "salary" :4000,
            "location" :"Uzbekistan"
        },
        {
            "id" :5,
            "title" : "Product Manager" ,
            "salary" :5000,
            "location" :"San Fransisco"
        }
    ]
}